wradex
